logging_utils/__init__.py
logging_utils/logging_utils.py
tests/__init__.py
tests/context.py
tests/logdecorator_test.py
ni_logging_utils-0.0.3.dist-info/LICENSE
ni_logging_utils-0.0.3.dist-info/METADATA
ni_logging_utils-0.0.3.dist-info/WHEEL
ni_logging_utils-0.0.3.dist-info/top_level.txt
ni_logging_utils-0.0.3.dist-info/RECORD
