Metadata-Version: 2.1
Name: ni-logging-utils
Version: 0.0.3
Summary: A small tools to log
Home-page: https://gitlab.com/naturalinterface/logging_utils
Author: Primael Bruant
Author-email: primael.bruant@gmail.com
License: UNKNOWN
Platform: UNKNOWN
Classifier: Programming Language :: Python :: 3
Classifier: License :: OSI Approved :: MIT License
Classifier: Operating System :: OS Independent
Requires-Python: >=3.6
